{
  "poc_posts": [
    {
      "id": 1,
      "title": "hello"
    }
  ],
  "poc_profile": {
    "name": "typicode"
  },
  "mcheyne": [
    {"id": 1, "secret01": "Genesis 1 ", "secret02": " Matthew 1", "family01": "Ezra 1 ", "family02": " Acts 1"},
{"id": 2, "secret01": "Genesis 2 ", "secret02": " Matthew 2", "family01": "Ezra 2 ", "family02": " Acts 2"},
{"id": 3, "secret01": "Genesis 3 ", "secret02": " Matthew 3", "family01": "Ezra 3 ", "family02": " Acts 3"},
{"id": 4, "secret01": "Genesis 4 ", "secret02": " Matthew 4", "family01": "Ezra 4 ", "family02": " Acts 4"},
{"id": 5, "secret01": "Genesis 5 ", "secret02": " Matthew 5", "family01": "Ezra 5 ", "family02": " Acts 5"},
{"id": 6, "secret01": "Genesis 6 ", "secret02": " Matthew 6", "family01": "Ezra 6 ", "family02": " Acts 6"},
{"id": 7, "secret01": "Genesis 7 ", "secret02": " Matthew 7", "family01": "Ezra 7 ", "family02": " Acts 7"},
{"id": 8, "secret01": "Genesis 8 ", "secret02": " Matthew 8", "family01": "Ezra 8 ", "family02": " Acts 8"},
{"id": 9, "secret01": "Genesis 9-10 ", "secret02": " Matthew 9", "family01": "Ezra 9 ", "family02": " Acts 9"},
{"id": 10, "secret01": "Genesis 11 ", "secret02": " Matthew 10", "family01": "Ezra 10 ", "family02": " Acts 10"},
{"id": 11, "secret01": "Genesis 12 ", "secret02": " Matthew 11", "family01": "Nehemiah 1 ", "family02": " Acts 11"},
{"id": "12", "secret01": "Genesis 13 ", "secret02": " Matthew 12", "family01": "Nehemiah 2 ", "family02": " Acts 12"},
{"id": "13", "secret01": "Genesis 14 ", "secret02": " Matthew 13", "family01": "Nehemiah 3 ", "family02": " Acts 13"},
{"id": "14", "secret01": "Genesis 15 ", "secret02": " Matthew 14", "family01": "Nehemiah 4 ", "family02": " Acts 14"},
{"id": "15", "secret01": "Genesis 16 ", "secret02": " Matthew 15", "family01": "Nehemiah 5 ", "family02": " Acts 15"},
{"id": "16", "secret01": "Genesis 17 ", "secret02": " Matthew 16", "family01": "Nehemiah 6 ", "family02": " Acts 16"},
{"id": "17", "secret01": "Genesis 18 ", "secret02": " Matthew 17", "family01": "Nehemiah 7 ", "family02": " Acts 17"},
{"id": "18", "secret01": "Genesis 19 ", "secret02": " Matthew 18", "family01": "Nehemiah 8 ", "family02": " Acts 18"},
{"id": "19", "secret01": "Genesis 20 ", "secret02": " Matthew 19", "family01": "Nehemiah 9 ", "family02": " Acts 19"},
{"id": "20", "secret01": "Genesis 21 ", "secret02": " Matthew 20", "family01": "Nehemiah 10 ", "family02": " Acts 20"},
{"id": "21", "secret01": "Genesis 22 ", "secret02": " Matthew 21", "family01": "Nehemiah 11 ", "family02": " Acts 21"},
{"id": "22", "secret01": "Genesis 23 ", "secret02": " Matthew 22", "family01": "Nehemiah 12 ", "family02": " Acts 22"},
{"id": "23", "secret01": "Genesis 24 ", "secret02": " Matthew 23", "family01": "Nehemiah 13 ", "family02": " Acts 23"},
{"id": "24", "secret01": "Genesis 25 ", "secret02": " Matthew 24", "family01": "Esther 1 ", "family02": " Acts 24"},
{"id": "25", "secret01": "Genesis 26 ", "secret02": " Matthew 25", "family01": "Esther 2 ", "family02": " Acts 25"},
{"id": "26", "secret01": "Genesis 27 ", "secret02": " Matthew 26", "family01": "Esther 3 ", "family02": " Acts 26"},
{"id": "27", "secret01": "Genesis 28 ", "secret02": " Matthew 27", "family01": "Esther 4 ", "family02": " Acts 27"},
{"id": "28", "secret01": "Genesis 29 ", "secret02": " Matthew 28", "family01": "Esther 5 ", "family02": " Acts 28"},
{"id": "29", "secret01": "Genesis 30 ", "secret02": " Mark 1", "family01": "Esther 6 ", "family02": " Romans 1"}
  ]  
}
